cli.py
formatter.py
json_to_jsonl.py
json_prompt_formatter-1.0.0.data/data/prompts/branding_prompts.txt
json_prompt_formatter-1.0.0.data/data/templates/copywriter_template.json
json_prompt_formatter-1.0.0.data/data/templates/designer_template.json
json_prompt_formatter-1.0.0.data/data/templates/founder_template.json
json_prompt_formatter-1.0.0.data/data/templates/marketer_template.json
json_prompt_formatter-1.0.0.data/data/templates/openai_template.json
json_prompt_formatter-1.0.0.data/data/templates/product_designer_template.json
json_prompt_formatter-1.0.0.data/data/templates/prompt_engineer_template.json
json_prompt_formatter-1.0.0.dist-info/licenses/LICENSE
json_prompt_formatter-1.0.0.dist-info/METADATA
json_prompt_formatter-1.0.0.dist-info/WHEEL
json_prompt_formatter-1.0.0.dist-info/entry_points.txt
json_prompt_formatter-1.0.0.dist-info/top_level.txt
json_prompt_formatter-1.0.0.dist-info/RECORD
