Metadata-Version: 2.4
Name: json-prompt-formatter
Version: 1.0.0
Summary: CLI tool for formatting prompts using JSON templates for different use cases
Home-page: https://github.com/SemTiOne/json_prompt_formatter
Author: SemTiOne
Author-email: emphyst80@gmail.com
Project-URL: Bug Tracker, https://github.com/SemTiOne/json_prompt_formatter/issues
Project-URL: Documentation, https://github.com/SemTiOne/json_prompt_formatter#readme
Project-URL: Source Code, https://github.com/SemTiOne/json_prompt_formatter
Keywords: prompt-engineering,json,cli,ai,chatgpt,openai,formatting,templates,automation,prompt-templates,developer-tools
Classifier: Development Status :: 4 - Beta
Classifier: Intended Audience :: Developers
Classifier: Topic :: Software Development :: Libraries :: Python Modules
Classifier: Topic :: Text Processing
Classifier: Topic :: Text Processing :: Markup
Classifier: Topic :: Utilities
Classifier: License :: OSI Approved :: MIT License
Classifier: Programming Language :: Python :: 3
Classifier: Programming Language :: Python :: 3.8
Classifier: Programming Language :: Python :: 3.9
Classifier: Programming Language :: Python :: 3.10
Classifier: Programming Language :: Python :: 3.11
Classifier: Programming Language :: Python :: 3.12
Classifier: Operating System :: OS Independent
Classifier: Environment :: Console
Requires-Python: >=3.8
License-File: LICENSE
Provides-Extra: dev
Requires-Dist: pytest>=6.0; extra == "dev"
Requires-Dist: pytest-cov>=2.0; extra == "dev"
Requires-Dist: black>=21.0; extra == "dev"
Requires-Dist: flake8>=3.8; extra == "dev"
Requires-Dist: mypy>=0.800; extra == "dev"
Requires-Dist: build>=0.7; extra == "dev"
Requires-Dist: twine>=3.0; extra == "dev"
Dynamic: author
Dynamic: author-email
Dynamic: classifier
Dynamic: description
Dynamic: description-content-type
Dynamic: home-page
Dynamic: keywords
Dynamic: license-file
Dynamic: project-url
Dynamic: provides-extra
Dynamic: requires-python
Dynamic: summary
